torch_pitch_shift/__init__.py
torch_pitch_shift/main.py
torch_pitch_shift-1.2.4.dist-info/LICENSE
torch_pitch_shift-1.2.4.dist-info/METADATA
torch_pitch_shift-1.2.4.dist-info/WHEEL
torch_pitch_shift-1.2.4.dist-info/top_level.txt
torch_pitch_shift-1.2.4.dist-info/RECORD
