Metadata-Version: 2.1
Name: torch_pitch_shift
Version: 1.2.4
Home-page: https://github.com/KentoNishi/torch-pitch-shift
Author: KentoNishi
Author-email: kento24gs@outlook.com
Classifier: Programming Language :: Python :: 3
Classifier: License :: OSI Approved :: MIT License
Classifier: Operating System :: OS Independent
Requires-Python: >=3.4
License-File: LICENSE
